{
    "Class": 284,
    "Previous_Class": 16,
    "Next_Class": 20,
    "Skill_1": 36,
    "Skill_1_Status": 40,
    "Skill_Step": 8,
    "Min_Sword_Rank": 184,
    "Min_Lance_Rank": 186,
    "Min_Axe_Rank": 188,
    "Min_Bow_Rank": 190,
    "Min_Knife_Rank": 192,
    "Min_Strike_Rank": 194,
    "Min_Fire_Rank": 196,
    "Min_Thunder_Rank": 198,
    "Min_Wind_Rank": 200,
    "Min_Light_Rank": 202,
    "Min_Dark_Rank": 204,
    "Min_Staff_Rank": 206,
    "Max_Sword_Rank": 208,
    "Max_Lance_Rank": 210,
    "Max_Axe_Rank": 212,
    "Max_Bow_Rank": 214,
    "Max_Knife_Rank": 216,
    "Max_Strike_Rank": 218,
    "Max_Fire_Rank": 220,
    "Max_Thunder_Rank": 222,
    "Max_Wind_Rank": 224,
    "Max_Light_Rank": 226,
    "Max_Dark_Rank": 228,
    "Max_Staff_Rank": 230,
    "Base_WT": 244,
    "Base_Move": 245,
    "Skill_Capacity": 247,
    "Max_HP": 260,
    "Max_STR": 261,
    "Max_MAG": 262,
    "Max_SKL": 263,
    "Max_SP": 264,
    "Max_LCK": 265,
    "Max_DEF": 266,
    "Max_RES": 267
}